LICENSE
MANIFEST.in
README.rst
buildout.cfg
requirements.txt
setup.py
version.txt
bob/__init__.py
bob.db.chasedb1.egg-info/PKG-INFO
bob.db.chasedb1.egg-info/SOURCES.txt
bob.db.chasedb1.egg-info/dependency_links.txt
bob.db.chasedb1.egg-info/entry_points.txt
bob.db.chasedb1.egg-info/not-zip-safe
bob.db.chasedb1.egg-info/requires.txt
bob.db.chasedb1.egg-info/top_level.txt
bob/db/__init__.py
bob/db/chasedb1/__init__.py
bob/db/chasedb1/chasedb1_db_default.json
bob/db/chasedb1/chasedb1_test.csv
bob/db/chasedb1/chasedb1_train.csv
bob/db/chasedb1/checkfiles.py
bob/db/chasedb1/create.py
bob/db/chasedb1/driver.py
bob/db/chasedb1/models.py
bob/db/chasedb1/query.py
bob/db/chasedb1/test.py
doc/guide.rst
doc/index.rst
doc/links.rst
doc/py_api.rst
doc/img/bob-128x128.png
doc/img/bob-favicon.ico
doc/img/bob-logo.png